autofunc/__init__.py
autofunc/autofunc.py
autofunc-0.1.0.dist-info/LICENSE
autofunc-0.1.0.dist-info/METADATA
autofunc-0.1.0.dist-info/WHEEL
autofunc-0.1.0.dist-info/top_level.txt
autofunc-0.1.0.dist-info/RECORD
