Metadata-Version: 2.1
Name: autofunc
Version: 0.1.0
Summary: Easily define python functions for structured LLM output
Home-page: https://github.com/nk412/autofunc
Author: Nagarjuna Kumarappan
Author-email: nagarjuna.412@gmail.com
License: MIT
Classifier: Development Status :: 4 - Beta
Classifier: Environment :: Console
Classifier: Intended Audience :: Developers
Classifier: License :: OSI Approved :: MIT License
Classifier: Operating System :: OS Independent
Classifier: Programming Language :: Python
License-File: LICENSE
Requires-Dist: pydantic ==2.4.2
Requires-Dist: openai ==1.12.0
